capture/__init__.py
capture/client.py
capture/constants.py
capture/data_types.py
capture/setup.py
capture/utils.py
data_capture-0.9.9.6.dist-info/METADATA
data_capture-0.9.9.6.dist-info/WHEEL
data_capture-0.9.9.6.dist-info/top_level.txt
data_capture-0.9.9.6.dist-info/RECORD
