Metadata-Version: 2.1
Name: data-capture
Version: 0.9.9.6
Summary: project descriptions here
Home-page: https://console.cloud.baidu-int.com/devops/icode/repos/baidu/themis/windmill-endpoint/tree/master
Author: zhoubohan
Author-email: zhoubohan@baidu.com
License: MIT
Platform: UNKNOWN
Classifier: Programming Language :: Python
Classifier: Programming Language :: Python :: 3
Classifier: Programming Language :: Python :: 3.7
Classifier: Programming Language :: Python :: 3.8
Classifier: Programming Language :: Python :: 3.9
Requires-Python: >=3.7
Requires-Dist: loguru (>=0.6.0)
Requires-Dist: Pillow (>=9.2.0)
Requires-Dist: numpy (>=1.21.6)
Requires-Dist: pydantic (>=1.10.4)
